{
  "algorithm_version": 2,
  "end_time": "Thu, 27 May 2021 01:14:55 GMT",
  "grade": "F",
  "hidden": false,
  "likelihood_indicator": "MEDIUM",
  "response_headers": {
    "Cache-Control": "max-age=1731",
    "Connection": "Keep-Alive",
    "Content-Type": "text/html; charset=iso-8859-1",
    "Date": "Thu, 27 May 2021 01:14:53 GMT",
    "ETag": "\"3902d42d1d024a9932cd7da839471f12\"",
    "Expires": "Thu, 27 May 2021 01:43:44 GMT",
    "Keep-Alive": "timeout=15, max=100",
    "Last-Modified": "Mon, 10 May 2021 07:38:11 GMT",
    "Pragma": "public",
    "Server": "Apache/2.2.10 (Linux/SUSE)",
    "Set-Cookie": "fe_typo_user=b532a589b4738648c96d0ea2a65ee29d; path=/",
    "Transfer-Encoding": "chunked",
    "X-Powered-By": "PHP/5.2.13"
  },
  "scan_id": 19349788,
  "score": 0,
  "start_time": "Thu, 27 May 2021 01:14:49 GMT",
  "state": "FINISHED",
  "status_code": 200,
  "tests_failed": 8,
  "tests_passed": 4,
  "tests_quantity": 12
}