{
  "algorithm_version": 2,
  "end_time": "Mon, 24 May 2021 00:07:28 GMT",
  "grade": "F",
  "hidden": false,
  "likelihood_indicator": "MEDIUM",
  "response_headers": {
    "Access-Control-Allow-Origin": "*",
    "Cache-Control": "private, no-cache, no-store, must-revalidate",
    "Connection": "keep-alive",
    "Content-Encoding": "gzip",
    "Content-Length": "22918",
    "Content-Type": "text/html;charset=UTF-8",
    "Date": "Mon, 24 May 2021 00:07:13 GMT",
    "Expires": "Thu, 01 Jan 1970 00:00:00 GMT",
    "Liferay-Portal": "Liferay Community Edition Portal 7.3.4 CE GA5 (Athanasius / Build 7304 / August 11, 2020)",
    "Pragma": "no-cache",
    "Set-Cookie": "JSESSIONID=6C74C3B18BEB130452AFDEA79DD93DA7; Path=/; HttpOnly, COOKIE_SUPPORT=yQ/aoiFowjTExmKLgNwcKTRgUwKImCTk3Xu9N90mZPg=; Max-Age=31536000; Expires=Tue, 24-May-2022 00:07:13 GMT; Path=/; HttpOnly, SERVERID=yQ/aoiFowjTExmKLgNwcKQ9g+hgu4tPW22sVS6XrtAg=; path=/",
    "X-Content-Type-Options": "nosniff",
    "X-Frame-Options": "SAMEORIGIN",
    "X-HW": "1621814833.cds078.sj3.hn,1621814833.cds049.sj3.sc,1621814833.cds049.sj3.p",
    "X-XSS-Protection": "1; mode=block"
  },
  "scan_id": 19298964,
  "score": 0,
  "start_time": "Mon, 24 May 2021 00:06:57 GMT",
  "state": "FINISHED",
  "status_code": 200,
  "tests_failed": 4,
  "tests_passed": 8,
  "tests_quantity": 12
}