{
  "algorithm_version": 2,
  "end_time": "Fri, 26 Mar 2021 02:22:50 GMT",
  "grade": "F",
  "hidden": false,
  "likelihood_indicator": "MEDIUM",
  "response_headers": {
    "Connection": "Keep-Alive",
    "Content-Encoding": "gzip",
    "Content-Length": "12252",
    "Content-Type": "text/html; charset=UTF-8",
    "Date": "Fri, 26 Mar 2021 02:22:42 GMT",
    "Keep-Alive": "timeout=3, max=500",
    "Last-Modified": "Fri, 26 Mar 2021 02:22:42 GMT",
    "Server": "Apache",
    "Vary": "Accept-Encoding"
  },
  "scan_id": 18388669,
  "score": 0,
  "start_time": "Fri, 26 Mar 2021 02:22:38 GMT",
  "state": "FINISHED",
  "status_code": 200,
  "tests_failed": 7,
  "tests_passed": 5,
  "tests_quantity": 12
}