{
  "algorithm_version": 2,
  "end_time": "Fri, 28 May 2021 01:24:33 GMT",
  "grade": "F",
  "hidden": false,
  "likelihood_indicator": "MEDIUM",
  "response_headers": {
    "Content-Length": "35137",
    "Content-Type": "text/html",
    "Date": "Fri, 28 May 2021 01:24:32 GMT",
    "Feature-Policy": "microphone 'none'; camera 'none'; usb 'none'; payment 'none'",
    "Set-Cookie": "TS011b0901=018ac16f67ee1eab835b88f542fbb962debcf1f05ac072b0e46f9a77166be753b993b2d92f214ee56829a9c98eef142f0aa49a1591; Path=/; Domain=.www.donostia.eus; Secure; HTTPOnly",
    "Strict-Transport-Security": "max-age=16070400; includeSubDomains",
    "X-Content-Type-Option": "nosniff",
    "X-Content-Type-Options": "nosniff",
    "X-Frame-Options": "SAMEORIGIN"
  },
  "scan_id": 19364499,
  "score": 15,
  "start_time": "Fri, 28 May 2021 01:24:25 GMT",
  "state": "FINISHED",
  "status_code": 200,
  "tests_failed": 3,
  "tests_passed": 9,
  "tests_quantity": 12
}