{
  "algorithm_version": 2,
  "end_time": "Mon, 21 Jun 2021 00:49:21 GMT",
  "grade": "F",
  "hidden": false,
  "likelihood_indicator": "MEDIUM",
  "response_headers": {
    "Cache-Control": "no-store, no-cache, must-revalidate",
    "Connection": "Keep-Alive",
    "Content-Encoding": "gzip",
    "Content-Length": "16780",
    "Content-Type": "text/html; charset=UTF-8",
    "Date": "Mon, 21 Jun 2021 00:48:40 GMT",
    "Expires": "Thu, 19 Nov 1981 08:52:00 GMT",
    "Keep-Alive": "timeout=5, max=100",
    "Link": "<https://www.toledo.es/wp-json/>; rel=\"https://api.w.org/\"",
    "Pragma": "no-cache",
    "Server": "Apache/2.4.6 (CentOS) OpenSSL/1.0.2k-fips PHP/7.0.32",
    "Set-Cookie": "mc_session_ids[default]=eb3b4452e59586dbdb728e68b16a28bf67c5ae67; expires=Mon, 21-Jun-2021 00:53:40 GMT; Max-Age=300; path=/; domain=.toledo.es; secure; HttpOnly, mc_session_ids[multi][0]=de4f379471a11117720c679f31048400bb45bfd2; expires=Mon, 21-Jun-2021 00:53:40 GMT; Max-Age=300; path=/; domain=.toledo.es, mc_session_ids[multi][1]=7d9578eeef2b298a84ce18d7d1b32bce63902ef4; expires=Mon, 21-Jun-2021 00:53:40 GMT; Max-Age=300; path=/; domain=.toledo.es, mc_session_ids[multi][2]=c188f4d364171376272b24fb1cdf68010e895612; expires=Mon, 21-Jun-2021 00:53:40 GMT; Max-Age=300; path=/; domain=.toledo.es, mc_session_ids[multi][3]=39ffff0dd8945d345a2b6ced3897ac4d97b858dd; expires=Mon, 21-Jun-2021 00:53:40 GMT; Max-Age=300; path=/; domain=.toledo.es, mc_session_ids[multi][4]=065a7140751155efa7899918b80ca8f67ecf267d; expires=Mon, 21-Jun-2021 00:53:40 GMT; Max-Age=300; path=/; domain=.toledo.es, PHPSESSID=394849cc6505490dd47db55e5500b11b; path=/, cf7msm_check=1; path=/; domain=.toledo.es",
    "Vary": "Accept-Encoding",
    "X-Powered-By": "PHP/7.0.32"
  },
  "scan_id": 19758169,
  "score": 0,
  "start_time": "Mon, 21 Jun 2021 00:48:35 GMT",
  "state": "FINISHED",
  "status_code": 200,
  "tests_failed": 7,
  "tests_passed": 5,
  "tests_quantity": 12
}