{
  "algorithm_version": 2,
  "end_time": "Mon, 19 Jul 2021 00:50:14 GMT",
  "grade": "F",
  "hidden": false,
  "likelihood_indicator": "MEDIUM",
  "response_headers": {
    "Accept-Ranges": "bytes",
    "Access-Control-Allow-Origin": "*",
    "Connection": "keep-alive",
    "Content-Type": "text/html",
    "Date": "Mon, 19 Jul 2021 00:50:11 GMT",
    "Last-Modified": "Tue, 26 Jan 2021 17:11:14 GMT",
    "Server": "Apache",
    "Transfer-Encoding": "chunked",
    "Via": "1.1 7249a40acbdf780c70c361e01c86fa64.cloudfront.net (CloudFront)",
    "X-Amz-Cf-Id": "p1lfNxqA6z7Ef7tl6FW1YndZqNdyRmjfimzJaNGmFVu2o9nWM5vwVg==",
    "X-Amz-Cf-Pop": "HIO50-C2",
    "X-Cache": "Miss from cloudfront",
    "X-Powered-By": "ModLayout/5.1"
  },
  "scan_id": 20314434,
  "score": 20,
  "start_time": "Mon, 19 Jul 2021 00:48:48 GMT",
  "state": "FINISHED",
  "status_code": 200,
  "tests_failed": 5,
  "tests_passed": 7,
  "tests_quantity": 12
}