{
  "algorithm_version": 2,
  "end_time": "Sat, 06 Mar 2021 09:12:18 GMT",
  "grade": "F",
  "hidden": true,
  "likelihood_indicator": "MEDIUM",
  "response_headers": {
    "Connection": "close",
    "Content-Type": "text/html;charset=ISO-8859-1",
    "Date": "Sat, 06 Mar 2021 09:12:14 GMT",
    "Server": "Apache-Coyote/1.1",
    "Set-Cookie": "JSESSIONID=6EB008B2FA46DA21C15DD16393605AF7; Path=/webdinamica/; HttpOnly",
    "Transfer-Encoding": "chunked"
  },
  "scan_id": 18064433,
  "score": 0,
  "start_time": "Sat, 06 Mar 2021 09:12:09 GMT",
  "state": "FINISHED",
  "status_code": 200,
  "tests_failed": 8,
  "tests_passed": 4,
  "tests_quantity": 12
}